pyoctonion/Pyoctonion.py
pyoctonion/__init__.py
pyoctonion-3.12.dist-info/METADATA
pyoctonion-3.12.dist-info/WHEEL
pyoctonion-3.12.dist-info/top_level.txt
pyoctonion-3.12.dist-info/RECORD
