Metadata-Version: 2.1
Name: pyoctonion
Version: 3.12
Summary: Octonion Number System
Author: Kalpa Madawa & Charith Atapattu
Author-email: charithnisanka@gmail.com
